{
    "profile": [
      {
        "id": 1,
        "name": "Павел ",
        "surname": "Брюханов",
        "salary": 1000
      },
      {
        "id": 2,
        "name": "Владимир",
        "surname": "Баласанян",
        "salary": 1000
      },
      {
        "id": 3,
        "name": "Ольга",
        "surname": "Петрова",
        "salary": 950
      },
  
      {
        "id": 4,
        "name": "Иван",
        "surname": "Иванов",
        "salary": 770
      },
      {
        "id": 5,
        "name": "Сергей",
        "surname": "Коновалов",
        "salary": 800
      },
      {
        "id": 6,
        "name": "Алексей",
        "surname": "Левченко",
        "salary": 900
      },
      {
        "id": 7,
        "name": "Андрей",
        "surname": "Фролов",
        "salary": 600
      },
      {
        "id": 8,
        "name": "Евгений",
        "surname": "Смирнов",
        "salary": 350
      },
      {
        "id": 9,
        "name": "Александр",
        "surname": "Мирный",
        "salary": 500
      },
      {
        "id": 10,
        "name": "Артём",
        "surname": "Коломийцев",
        "salary": 900
      }
    ]
  }